facelogin2/__init__.py
facelogin2-0.1.dist-info/LICENSE.txt
facelogin2-0.1.dist-info/METADATA
facelogin2-0.1.dist-info/WHEEL
facelogin2-0.1.dist-info/top_level.txt
facelogin2-0.1.dist-info/RECORD
