Metadata-Version: 2.1
Name: facelogin2
Version: 0.1
Summary: This my first time packaging
Home-page: UNKNOWN
Author: Alif Syafiq
Author-email: ahmadalif.syafiq@gmail.com
License: UNKNOWN
Platform: UNKNOWN
Classifier: Programming Language :: Python :: 3
Classifier: License :: OSI Approved :: MIT License
Classifier: Operating System :: OS Independent
License-File: LICENSE.txt
